<?xml version="1.0" encoding="utf-8"?>
<savedqueries xmlns:xsi="http://www.w3.org/2001/XMLSchema-instance">
  <savedquery>
    <IsCustomizable>1</IsCustomizable>
    <CanBeDeleted>1</CanBeDeleted>
    <isquickfindquery>0</isquickfindquery>
    <isprivate>0</isprivate>
    <isdefault>0</isdefault>
    <savedqueryid>{1017e053-3c8f-ec11-b400-6045bd93d2ef}</savedqueryid>
    <layoutxml>
      <grid name="resultset" jump="pg_name" select="1" icon="1" preview="1">
        <row name="result" id="pg_eventparticipationid">
          <cell name="pg_contactid" width="250" />
          <cell name="createdon" width="125" />
          <cell name="pg_comments" width="300" />
        </row>
      </grid>
    </layoutxml>
    <querytype>0</querytype>
    <fetchxml>
      <fetch version="1.0" mapping="logical">
        <entity name="pg_eventparticipation">
          <attribute name="pg_eventparticipationid" />
          <attribute name="createdon" />
          <filter type="and">
            <condition attribute="statecode" operator="eq" value="0" />
          </filter>
          <attribute name="pg_contactid" />
          <attribute name="pg_comments" />
        </entity>
      </fetch>
    </fetchxml>
    <IntroducedVersion>1.0.0.0</IntroducedVersion>
    <LocalizedNames>
      <LocalizedName description="Participations" languagecode="1033" />
    </LocalizedNames>
  </savedquery>
</savedqueries>