<?xml version="1.0" encoding="utf-8"?>
<WebResource xmlns:xsi="http://www.w3.org/2001/XMLSchema-instance">
  <WebResourceId>{b04a6ebf-361a-ed11-b83e-000d3aaeec66}</WebResourceId>
  <Name>pg_/image/event.svg</Name>
  <DisplayName>pg_/image/event.svg</DisplayName>
  <WebResourceType>11</WebResourceType>
  <IntroducedVersion>1.0.0.0</IntroducedVersion>
  <IsEnabledForMobileClient>1</IsEnabledForMobileClient>
  <IsAvailableForMobileOffline>0</IsAvailableForMobileOffline>
  <IsCustomizable>1</IsCustomizable>
  <CanBeDeleted>1</CanBeDeleted>
  <IsHidden>0</IsHidden>
  <FileName>/WebResources/pg_imageeventsvgB04A6EBF-361A-ED11-B83E-000D3AAEEC66</FileName>
</WebResource>